dingdong_sdk/__init__.py
dingdong_sdk/auth.py
dingdong_sdk-0.0.7.dist-info/METADATA
dingdong_sdk-0.0.7.dist-info/WHEEL
dingdong_sdk-0.0.7.dist-info/top_level.txt
dingdong_sdk-0.0.7.dist-info/RECORD
