Metadata-Version: 2.1
Name: dingdong-sdk
Version: 0.0.7
Summary: The DingDong SDK
Home-page: https://bitbucket.org/ctiteam/dingdong-sdk
Author: Centre of Technology and Innovation
Author-email: cti@apiit.edu.my
Classifier: Intended Audience :: Developers
Classifier: Programming Language :: Python :: 3
Classifier: License :: OSI Approved :: MIT License
Classifier: Operating System :: OS Independent
Requires-Dist: requests
